WazeRouteCalculator/WazeRouteCalculator.py
WazeRouteCalculator/__init__.py
WazeRouteCalculator/__version__.py
WazeRouteCalculator-0.15.dist-info/LICENSE
WazeRouteCalculator-0.15.dist-info/METADATA
WazeRouteCalculator-0.15.dist-info/WHEEL
WazeRouteCalculator-0.15.dist-info/top_level.txt
WazeRouteCalculator-0.15.dist-info/RECORD
