Metadata-Version: 2.1
Name: WazeRouteCalculator
Version: 0.15
Summary: Calculate actual route time and distance with waze api.
Home-page: https://github.com/kovacsbalu/WazeRouteCalculator
Author: Balint Kovacs
Author-email: kovacsbalu@gmail.com
License: GNU GPL v3
Download-URL: https://github.com/kovacsbalu/WazeRouteCalculator/tarball/0.15
Keywords: waze,route,calculator
Platform: UNKNOWN
License-File: LICENSE
Requires-Dist: requests
